README.md
setup.py
sisenseautomation/__init__.py
sisenseautomation/exceptions.py
sisenseautomation.egg-info/PKG-INFO
sisenseautomation.egg-info/SOURCES.txt
sisenseautomation.egg-info/dependency_links.txt
sisenseautomation.egg-info/not-zip-safe
sisenseautomation.egg-info/requires.txt
sisenseautomation.egg-info/top_level.txt