Metadata-Version: 2.1
Name: sisenseautomation
Version: 0.0.1
Summary: Package for automating sisense tasks.
Home-page: https://github.com/cristhianmurcia182/sisense-automation
Author: cmurcia
Author-email: cmurcia@workforcelogiq.com
License: MIT
Keywords: configuration core yaml ini json environment
Platform: UNKNOWN
Classifier: Development Status :: 5 - Production/Stable
Classifier: License :: OSI Approved :: MIT License
Classifier: Programming Language :: Python :: 3
Classifier: Operating System :: OS Independent
